eis_pointing/__init__.py
eis_pointing/driver.py
eis_pointing/driver_cli.py
eis_pointing/eis_aia_emission.py
eis_pointing/eis_aia_registration.py
eis_pointing/export_windata.pro
eis_pointing/prep.pro
eis_pointing/coregister/__init__.py
eis_pointing/coregister/images.py
eis_pointing/coregister/rasters.py
eis_pointing/coregister/slits.py
eis_pointing/coregister/tools.py
eis_pointing/utils/__init__.py
eis_pointing/utils/aia.py
eis_pointing/utils/aia_raster.py
eis_pointing/utils/cli.py
eis_pointing/utils/eis.py
eis_pointing/utils/files.py
eis_pointing/utils/idl.py
eis_pointing/utils/misc.py
eis_pointing/utils/num.py
eis_pointing/utils/plots.py
eis_pointing/utils/sun.py
eis_pointing-2025.4.25.dist-info/licenses/LICENSE.txt
eis_pointing-2025.4.25.dist-info/METADATA
eis_pointing-2025.4.25.dist-info/WHEEL
eis_pointing-2025.4.25.dist-info/entry_points.txt
eis_pointing-2025.4.25.dist-info/top_level.txt
eis_pointing-2025.4.25.dist-info/RECORD
