Metadata-Version: 2.4
Name: eis_pointing
Version: 2025.4.25
Summary: Tools to correct the pointing of Hinode/EIS
Author-email: Gabriel Pelouze <gabriel.pelouze@ias.u-psud.fr>
License-Expression: MIT
Project-URL: Homepage, https://github.com/gpelouze/eis_pointing
Classifier: Programming Language :: Python :: 3
Classifier: Operating System :: OS Independent
Classifier: Intended Audience :: Science/Research
Classifier: Topic :: Scientific/Engineering :: Astronomy
Requires-Python: >=3.5
License-File: LICENSE.txt
Requires-Dist: astropy>=3.0
Requires-Dist: python-dateutil>=2.7
Requires-Dist: matplotlib>=2.0
Requires-Dist: numpy>=1.15
Requires-Dist: requests>=2.19
Requires-Dist: scipy>=1.0
Requires-Dist: PyYAML>=3.13
Requires-Dist: pySitools2==1.0.0
Dynamic: license-file
